AUTHORS
COPYING
README.rst
iotlab-ssh
open-a8-cli
setup.cfg
setup.py
iotlabsshcli/__init__.py
iotlabsshcli/open_linux.py
iotlabsshcli.egg-info/PKG-INFO
iotlabsshcli.egg-info/SOURCES.txt
iotlabsshcli.egg-info/dependency_links.txt
iotlabsshcli.egg-info/requires.txt
iotlabsshcli.egg-info/top_level.txt
iotlabsshcli/parser/__init__.py
iotlabsshcli/parser/open_linux_parser.py
iotlabsshcli/sshlib/__init__.py
iotlabsshcli/sshlib/open_linux_ssh.py
iotlabsshcli/tests/__init__.py
iotlabsshcli/tests/iotlabsshcli_mock.py
iotlabsshcli/tests/open_linux_parser_test.py
iotlabsshcli/tests/open_linux_ssh_test.py
iotlabsshcli/tests/open_linux_test.py