Metadata-Version: 2.1
Name: iotlabsshcli
Version: 1.1.0
Summary: IoT-LAB testbed ssh command-line client
Home-page: http://www.iot-lab.info
Author: IoT-LAB Team
Author-email: admin@iot-lab.info
License: CeCILL v2.1
Download-URL: http://github.com/iot-lab/ssh-cli-tools/
Platform: UNKNOWN
Classifier: Development Status :: 5 - Production/Stable
Classifier: Programming Language :: Python
Classifier: Programming Language :: Python :: 3
Classifier: Intended Audience :: End Users/Desktop
Classifier: Environment :: Console
Classifier: Topic :: Utilities
